trekit/__init__.py
trekit-0.0.1.dist-info/LICENSE
trekit-0.0.1.dist-info/METADATA
trekit-0.0.1.dist-info/WHEEL
trekit-0.0.1.dist-info/top_level.txt
trekit-0.0.1.dist-info/RECORD
